{
    "url": "https://www.anapioficeandfire.com/api/characters/1280",
    "name": "Colemon",
    "gender": "Male",
    "culture": "",
    "born": "",
    "died": "",
    "titles": [
        "Maester"
    ],
    "aliases": [
        ""
    ],
    "father": "",
    "mother": "",
    "spouse": "",
    "allegiances": [
        "https://www.anapioficeandfire.com/api/houses/7"
    ],
    "books": [
        "https://www.anapioficeandfire.com/api/books/1",
        "https://www.anapioficeandfire.com/api/books/2",
        "https://www.anapioficeandfire.com/api/books/3",
        "https://www.anapioficeandfire.com/api/books/5",
        "https://www.anapioficeandfire.com/api/books/8"
    ],
    "povBooks": [],
    "tvSeries": [
        ""
    ],
    "playedBy": [
        ""
    ]
}
